{
  "id": "parse_json",
  "source_file": "parse_json.py",
  "category": "text",
  "display_name": "Parse JSON",
  "description": "Parse a JSON string into a Python dictionary or list.",
  "is_collapsed": false,
  "inputs": {
    "json_string": {
      "type": "str",
      "required": true,
      "description": "Input parameter: json_string"
    }
  },
  "outputs": {
    "data": {
      "type": "json",
      "description": "Output: data"
    }
  },
  "dependencies": {
    "python": [],
    "system": []
  },
  "version": "1.0.0",
  "author": "FabricFlow Team",
  "contributors": [],
  "created_at": "2026-03-12",
  "updated_at": "2026-03-12",
  "tags": [
    "text"
  ]
}